{
  "formatVersion": 1,
  "database": {
    "version": 48,
    "identityHash": "0f958ba55579b89c341335658fd01d2a",
    "entities": [
      {
        "tableName": "sensor_attributes",
        "createSql": "CREATE TABLE IF NOT EXISTS `${TABLE_NAME}` (`sensor_id` TEXT NOT NULL, `name` TEXT NOT NULL, `value` TEXT NOT NULL, `value_type` TEXT NOT NULL, PRIMARY KEY(`sensor_id`, `name`))",
        "fields": [
          {
            "fieldPath": "sensorId",
            "columnName": "sensor_id",
            "affinity": "TEXT",
            "notNull": true
          },
          {
            "fieldPath": "name",
            "columnName": "name",
            "affinity": "TEXT",
            "notNull": true
          },
          {
            "fieldPath": "value",
            "columnName": "value",
            "affinity": "TEXT",
            "notNull": true
          },
          {
            "fieldPath": "valueType",
            "columnName": "value_type",
            "affinity": "TEXT",
            "notNull": true
          }
        ],
        "primaryKey": {
          "autoGenerate": false,
          "columnNames": [
            "sensor_id",
            "name"
          ]
        },
        "indices": [],
        "foreignKeys": []
      },
      {
        "tableName": "authentication_list",
        "createSql": "CREATE TABLE IF NOT EXISTS `${TABLE_NAME}` (`host` TEXT NOT NULL, `username` TEXT NOT NULL, `password` TEXT NOT NULL, PRIMARY KEY(`host`))",
        "fields": [
          {
            "fieldPath": "host",
            "columnName": "host",
            "affinity": "TEXT",
            "notNull": true
          },
          {
            "fieldPath": "username",
            "columnName": "username",
            "affinity": "TEXT",
            "notNull": true
          },
          {
            "fieldPath": "password",
            "columnName": "password",
            "affinity": "TEXT",
            "notNull": true
          }
        ],
        "primaryKey": {
          "autoGenerate": false,
          "columnNames": [
            "host"
          ]
        },
        "indices": [],
        "foreignKeys": []
      },
      {
        "tableName": "sensors",
        "createSql": "CREATE TABLE IF NOT EXISTS `${TABLE_NAME}` (`id` TEXT NOT NULL, `server_id` INTEGER NOT NULL DEFAULT 0, `enabled` INTEGER NOT NULL, `registered` INTEGER DEFAULT NULL, `state` TEXT NOT NULL, `last_sent_state` TEXT DEFAULT NULL, `last_sent_icon` TEXT DEFAULT NULL, `state_type` TEXT NOT NULL, `type` TEXT NOT NULL, `icon` TEXT NOT NULL, `name` TEXT NOT NULL, `device_class` TEXT, `unit_of_measurement` TEXT, `state_class` TEXT, `entity_category` TEXT, `core_registration` TEXT, `app_registration` TEXT, PRIMARY KEY(`id`, `server_id`))",
        "fields": [
          {
            "fieldPath": "id",
            "columnName": "id",
            "affinity": "TEXT",
            "notNull": true
          },
          {
            "fieldPath": "serverId",
            "columnName": "server_id",
            "affinity": "INTEGER",
            "notNull": true,
            "defaultValue": "0"
          },
          {
            "fieldPath": "enabled",
            "columnName": "enabled",
            "affinity": "INTEGER",
            "notNull": true
          },
          {
            "fieldPath": "registered",
            "columnName": "registered",
            "affinity": "INTEGER",
            "notNull": false,
            "defaultValue": "NULL"
          },
          {
            "fieldPath": "state",
            "columnName": "state",
            "affinity": "TEXT",
            "notNull": true
          },
          {
            "fieldPath": "lastSentState",
            "columnName": "last_sent_state",
            "affinity": "TEXT",
            "notNull": false,
            "defaultValue": "NULL"
          },
          {
            "fieldPath": "lastSentIcon",
            "columnName": "last_sent_icon",
            "affinity": "TEXT",
            "notNull": false,
            "defaultValue": "NULL"
          },
          {
            "fieldPath": "stateType",
            "columnName": "state_type",
            "affinity": "TEXT",
            "notNull": true
          },
          {
            "fieldPath": "type",
            "columnName": "type",
            "affinity": "TEXT",
            "notNull": true
          },
          {
            "fieldPath": "icon",
            "columnName": "icon",
            "affinity": "TEXT",
            "notNull": true
          },
          {
            "fieldPath": "name",
            "columnName": "name",
            "affinity": "TEXT",
            "notNull": true
          },
          {
            "fieldPath": "deviceClass",
            "columnName": "device_class",
            "affinity": "TEXT",
            "notNull": false
          },
          {
            "fieldPath": "unitOfMeasurement",
            "columnName": "unit_of_measurement",
            "affinity": "TEXT",
            "notNull": false
          },
          {
            "fieldPath": "stateClass",
            "columnName": "state_class",
            "affinity": "TEXT",
            "notNull": false
          },
          {
            "fieldPath": "entityCategory",
            "columnName": "entity_category",
            "affinity": "TEXT",
            "notNull": false
          },
          {
            "fieldPath": "coreRegistration",
            "columnName": "core_registration",
            "affinity": "TEXT",
            "notNull": false
          },
          {
            "fieldPath": "appRegistration",
            "columnName": "app_registration",
            "affinity": "TEXT",
            "notNull": false
          }
        ],
        "primaryKey": {
          "autoGenerate": false,
          "columnNames": [
            "id",
            "server_id"
          ]
        },
        "indices": [],
        "foreignKeys": []
      },
      {
        "tableName": "sensor_settings",
        "createSql": "CREATE TABLE IF NOT EXISTS `${TABLE_NAME}` (`sensor_id` TEXT NOT NULL, `name` TEXT NOT NULL, `value` TEXT NOT NULL, `value_type` TEXT NOT NULL, `enabled` INTEGER NOT NULL, `entries` TEXT NOT NULL, PRIMARY KEY(`sensor_id`, `name`))",
        "fields": [
          {
            "fieldPath": "sensorId",
            "columnName": "sensor_id",
            "affinity": "TEXT",
            "notNull": true
          },
          {
            "fieldPath": "name",
            "columnName": "name",
            "affinity": "TEXT",
            "notNull": true
          },
          {
            "fieldPath": "value",
            "columnName": "value",
            "affinity": "TEXT",
            "notNull": true
          },
          {
            "fieldPath": "valueType",
            "columnName": "value_type",
            "affinity": "TEXT",
            "notNull": true
          },
          {
            "fieldPath": "enabled",
            "columnName": "enabled",
            "affinity": "INTEGER",
            "notNull": true
          },
          {
            "fieldPath": "entries",
            "columnName": "entries",
            "affinity": "TEXT",
            "notNull": true
          }
        ],
        "primaryKey": {
          "autoGenerate": false,
          "columnNames": [
            "sensor_id",
            "name"
          ]
        },
        "indices": [],
        "foreignKeys": []
      },
      {
        "tableName": "button_widgets",
        "createSql": "CREATE TABLE IF NOT EXISTS `${TABLE_NAME}` (`id` INTEGER NOT NULL, `server_id` INTEGER NOT NULL DEFAULT 0, `icon_name` TEXT NOT NULL, `domain` TEXT NOT NULL, `service` TEXT NOT NULL, `service_data` TEXT NOT NULL, `label` TEXT, `background_type` TEXT NOT NULL DEFAULT 'DAYNIGHT', `text_color` TEXT, `require_authentication` INTEGER NOT NULL DEFAULT 0, PRIMARY KEY(`id`))",
        "fields": [
          {
            "fieldPath": "id",
            "columnName": "id",
            "affinity": "INTEGER",
            "notNull": true
          },
          {
            "fieldPath": "serverId",
            "columnName": "server_id",
            "affinity": "INTEGER",
            "notNull": true,
            "defaultValue": "0"
          },
          {
            "fieldPath": "iconName",
            "columnName": "icon_name",
            "affinity": "TEXT",
            "notNull": true
          },
          {
            "fieldPath": "domain",
            "columnName": "domain",
            "affinity": "TEXT",
            "notNull": true
          },
          {
            "fieldPath": "service",
            "columnName": "service",
            "affinity": "TEXT",
            "notNull": true
          },
          {
            "fieldPath": "serviceData",
            "columnName": "service_data",
            "affinity": "TEXT",
            "notNull": true
          },
          {
            "fieldPath": "label",
            "columnName": "label",
            "affinity": "TEXT",
            "notNull": false
          },
          {
            "fieldPath": "backgroundType",
            "columnName": "background_type",
            "affinity": "TEXT",
            "notNull": true,
            "defaultValue": "'DAYNIGHT'"
          },
          {
            "fieldPath": "textColor",
            "columnName": "text_color",
            "affinity": "TEXT",
            "notNull": false
          },
          {
            "fieldPath": "requireAuthentication",
            "columnName": "require_authentication",
            "affinity": "INTEGER",
            "notNull": true,
            "defaultValue": "0"
          }
        ],
        "primaryKey": {
          "autoGenerate": false,
          "columnNames": [
            "id"
          ]
        },
        "indices": [],
        "foreignKeys": []
      },
      {
        "tableName": "camera_widgets",
        "createSql": "CREATE TABLE IF NOT EXISTS `${TABLE_NAME}` (`id` INTEGER NOT NULL, `server_id` INTEGER NOT NULL DEFAULT 0, `entity_id` TEXT NOT NULL, `tap_action` TEXT NOT NULL DEFAULT 'REFRESH', PRIMARY KEY(`id`))",
        "fields": [
          {
            "fieldPath": "id",
            "columnName": "id",
            "affinity": "INTEGER",
            "notNull": true
          },
          {
            "fieldPath": "serverId",
            "columnName": "server_id",
            "affinity": "INTEGER",
            "notNull": true,
            "defaultValue": "0"
          },
          {
            "fieldPath": "entityId",
            "columnName": "entity_id",
            "affinity": "TEXT",
            "notNull": true
          },
          {
            "fieldPath": "tapAction",
            "columnName": "tap_action",
            "affinity": "TEXT",
            "notNull": true,
            "defaultValue": "'REFRESH'"
          }
        ],
        "primaryKey": {
          "autoGenerate": false,
          "columnNames": [
            "id"
          ]
        },
        "indices": [],
        "foreignKeys": []
      },
      {
        "tableName": "media_player_controls_widgets",
        "createSql": "CREATE TABLE IF NOT EXISTS `${TABLE_NAME}` (`id` INTEGER NOT NULL, `server_id` INTEGER NOT NULL DEFAULT 0, `entity_id` TEXT NOT NULL, `label` TEXT, `show_skip` INTEGER NOT NULL, `show_seek` INTEGER NOT NULL, `show_volume` INTEGER NOT NULL, `show_source` INTEGER NOT NULL DEFAULT false, `background_type` TEXT NOT NULL DEFAULT 'DAYNIGHT', `text_color` TEXT, PRIMARY KEY(`id`))",
        "fields": [
          {
            "fieldPath": "id",
            "columnName": "id",
            "affinity": "INTEGER",
            "notNull": true
          },
          {
            "fieldPath": "serverId",
            "columnName": "server_id",
            "affinity": "INTEGER",
            "notNull": true,
            "defaultValue": "0"
          },
          {
            "fieldPath": "entityId",
            "columnName": "entity_id",
            "affinity": "TEXT",
            "notNull": true
          },
          {
            "fieldPath": "label",
            "columnName": "label",
            "affinity": "TEXT",
            "notNull": false
          },
          {
            "fieldPath": "showSkip",
            "columnName": "show_skip",
            "affinity": "INTEGER",
            "notNull": true
          },
          {
            "fieldPath": "showSeek",
            "columnName": "show_seek",
            "affinity": "INTEGER",
            "notNull": true
          },
          {
            "fieldPath": "showVolume",
            "columnName": "show_volume",
            "affinity": "INTEGER",
            "notNull": true
          },
          {
            "fieldPath": "showSource",
            "columnName": "show_source",
            "affinity": "INTEGER",
            "notNull": true,
            "defaultValue": "false"
          },
          {
            "fieldPath": "backgroundType",
            "columnName": "background_type",
            "affinity": "TEXT",
            "notNull": true,
            "defaultValue": "'DAYNIGHT'"
          },
          {
            "fieldPath": "textColor",
            "columnName": "text_color",
            "affinity": "TEXT",
            "notNull": false
          }
        ],
        "primaryKey": {
          "autoGenerate": false,
          "columnNames": [
            "id"
          ]
        },
        "indices": [],
        "foreignKeys": []
      },
      {
        "tableName": "static_widget",
        "createSql": "CREATE TABLE IF NOT EXISTS `${TABLE_NAME}` (`id` INTEGER NOT NULL, `server_id` INTEGER NOT NULL DEFAULT 0, `entity_id` TEXT NOT NULL, `attribute_ids` TEXT, `label` TEXT, `text_size` REAL NOT NULL, `state_separator` TEXT NOT NULL, `attribute_separator` TEXT NOT NULL, `tap_action` TEXT NOT NULL DEFAULT 'REFRESH', `last_update` TEXT NOT NULL, `background_type` TEXT NOT NULL DEFAULT 'DAYNIGHT', `text_color` TEXT, PRIMARY KEY(`id`))",
        "fields": [
          {
            "fieldPath": "id",
            "columnName": "id",
            "affinity": "INTEGER",
            "notNull": true
          },
          {
            "fieldPath": "serverId",
            "columnName": "server_id",
            "affinity": "INTEGER",
            "notNull": true,
            "defaultValue": "0"
          },
          {
            "fieldPath": "entityId",
            "columnName": "entity_id",
            "affinity": "TEXT",
            "notNull": true
          },
          {
            "fieldPath": "attributeIds",
            "columnName": "attribute_ids",
            "affinity": "TEXT",
            "notNull": false
          },
          {
            "fieldPath": "label",
            "columnName": "label",
            "affinity": "TEXT",
            "notNull": false
          },
          {
            "fieldPath": "textSize",
            "columnName": "text_size",
            "affinity": "REAL",
            "notNull": true
          },
          {
            "fieldPath": "stateSeparator",
            "columnName": "state_separator",
            "affinity": "TEXT",
            "notNull": true
          },
          {
            "fieldPath": "attributeSeparator",
            "columnName": "attribute_separator",
            "affinity": "TEXT",
            "notNull": true
          },
          {
            "fieldPath": "tapAction",
            "columnName": "tap_action",
            "affinity": "TEXT",
            "notNull": true,
            "defaultValue": "'REFRESH'"
          },
          {
            "fieldPath": "lastUpdate",
            "columnName": "last_update",
            "affinity": "TEXT",
            "notNull": true
          },
          {
            "fieldPath": "backgroundType",
            "columnName": "background_type",
            "affinity": "TEXT",
            "notNull": true,
            "defaultValue": "'DAYNIGHT'"
          },
          {
            "fieldPath": "textColor",
            "columnName": "text_color",
            "affinity": "TEXT",
            "notNull": false
          }
        ],
        "primaryKey": {
          "autoGenerate": false,
          "columnNames": [
            "id"
          ]
        },
        "indices": [],
        "foreignKeys": []
      },
      {
        "tableName": "template_widgets",
        "createSql": "CREATE TABLE IF NOT EXISTS `${TABLE_NAME}` (`id` INTEGER NOT NULL, `server_id` INTEGER NOT NULL DEFAULT 0, `template` TEXT NOT NULL, `text_size` REAL NOT NULL DEFAULT 12.0, `last_update` TEXT NOT NULL, `background_type` TEXT NOT NULL DEFAULT 'DAYNIGHT', `text_color` TEXT, PRIMARY KEY(`id`))",
        "fields": [
          {
            "fieldPath": "id",
            "columnName": "id",
            "affinity": "INTEGER",
            "notNull": true
          },
          {
            "fieldPath": "serverId",
            "columnName": "server_id",
            "affinity": "INTEGER",
            "notNull": true,
            "defaultValue": "0"
          },
          {
            "fieldPath": "template",
            "columnName": "template",
            "affinity": "TEXT",
            "notNull": true
          },
          {
            "fieldPath": "textSize",
            "columnName": "text_size",
            "affinity": "REAL",
            "notNull": true,
            "defaultValue": "12.0"
          },
          {
            "fieldPath": "lastUpdate",
            "columnName": "last_update",
            "affinity": "TEXT",
            "notNull": true
          },
          {
            "fieldPath": "backgroundType",
            "columnName": "background_type",
            "affinity": "TEXT",
            "notNull": true,
            "defaultValue": "'DAYNIGHT'"
          },
          {
            "fieldPath": "textColor",
            "columnName": "text_color",
            "affinity": "TEXT",
            "notNull": false
          }
        ],
        "primaryKey": {
          "autoGenerate": false,
          "columnNames": [
            "id"
          ]
        },
        "indices": [],
        "foreignKeys": []
      },
      {
        "tableName": "history_widgets",
        "createSql": "CREATE TABLE IF NOT EXISTS `${TABLE_NAME}` (`id` INTEGER NOT NULL, `server_id` INTEGER NOT NULL DEFAULT 0, `entity_id` TEXT NOT NULL, `label` TEXT, `text_size` REAL NOT NULL, `last_update` TEXT NOT NULL, `background_type` TEXT NOT NULL DEFAULT 'DAYNIGHT', `text_color` TEXT, PRIMARY KEY(`id`))",
        "fields": [
          {
            "fieldPath": "id",
            "columnName": "id",
            "affinity": "INTEGER",
            "notNull": true
          },
          {
            "fieldPath": "serverId",
            "columnName": "server_id",
            "affinity": "INTEGER",
            "notNull": true,
            "defaultValue": "0"
          },
          {
            "fieldPath": "entityId",
            "columnName": "entity_id",
            "affinity": "TEXT",
            "notNull": true
          },
          {
            "fieldPath": "label",
            "columnName": "label",
            "affinity": "TEXT",
            "notNull": false
          },
          {
            "fieldPath": "textSize",
            "columnName": "text_size",
            "affinity": "REAL",
            "notNull": true
          },
          {
            "fieldPath": "lastUpdate",
            "columnName": "last_update",
            "affinity": "TEXT",
            "notNull": true
          },
          {
            "fieldPath": "backgroundType",
            "columnName": "background_type",
            "affinity": "TEXT",
            "notNull": true,
            "defaultValue": "'DAYNIGHT'"
          },
          {
            "fieldPath": "textColor",
            "columnName": "text_color",
            "affinity": "TEXT",
            "notNull": false
          }
        ],
        "primaryKey": {
          "autoGenerate": false,
          "columnNames": [
            "id"
          ]
        },
        "indices": [],
        "foreignKeys": []
      },
      {
        "tableName": "notification_history",
        "createSql": "CREATE TABLE IF NOT EXISTS `${TABLE_NAME}` (`id` INTEGER PRIMARY KEY AUTOINCREMENT NOT NULL, `received` INTEGER NOT NULL, `message` TEXT NOT NULL, `data` TEXT NOT NULL, `source` TEXT NOT NULL, `server_id` INTEGER)",
        "fields": [
          {
            "fieldPath": "id",
            "columnName": "id",
            "affinity": "INTEGER",
            "notNull": true
          },
          {
            "fieldPath": "received",
            "columnName": "received",
            "affinity": "INTEGER",
            "notNull": true
          },
          {
            "fieldPath": "message",
            "columnName": "message",
            "affinity": "TEXT",
            "notNull": true
          },
          {
            "fieldPath": "data",
            "columnName": "data",
            "affinity": "TEXT",
            "notNull": true
          },
          {
            "fieldPath": "source",
            "columnName": "source",
            "affinity": "TEXT",
            "notNull": true
          },
          {
            "fieldPath": "serverId",
            "columnName": "server_id",
            "affinity": "INTEGER",
            "notNull": false
          }
        ],
        "primaryKey": {
          "autoGenerate": true,
          "columnNames": [
            "id"
          ]
        },
        "indices": [],
        "foreignKeys": []
      },
      {
        "tableName": "location_history",
        "createSql": "CREATE TABLE IF NOT EXISTS `${TABLE_NAME}` (`id` INTEGER PRIMARY KEY AUTOINCREMENT NOT NULL, `created` INTEGER NOT NULL, `trigger` TEXT NOT NULL, `result` TEXT NOT NULL, `latitude` REAL, `longitude` REAL, `location_name` TEXT, `accuracy` INTEGER, `data` TEXT, `server_id` INTEGER)",
        "fields": [
          {
            "fieldPath": "id",
            "columnName": "id",
            "affinity": "INTEGER",
            "notNull": true
          },
          {
            "fieldPath": "created",
            "columnName": "created",
            "affinity": "INTEGER",
            "notNull": true
          },
          {
            "fieldPath": "trigger",
            "columnName": "trigger",
            "affinity": "TEXT",
            "notNull": true
          },
          {
            "fieldPath": "result",
            "columnName": "result",
            "affinity": "TEXT",
            "notNull": true
          },
          {
            "fieldPath": "latitude",
            "columnName": "latitude",
            "affinity": "REAL",
            "notNull": false
          },
          {
            "fieldPath": "longitude",
            "columnName": "longitude",
            "affinity": "REAL",
            "notNull": false
          },
          {
            "fieldPath": "locationName",
            "columnName": "location_name",
            "affinity": "TEXT",
            "notNull": false
          },
          {
            "fieldPath": "accuracy",
            "columnName": "accuracy",
            "affinity": "INTEGER",
            "notNull": false
          },
          {
            "fieldPath": "data",
            "columnName": "data",
            "affinity": "TEXT",
            "notNull": false
          },
          {
            "fieldPath": "serverId",
            "columnName": "server_id",
            "affinity": "INTEGER",
            "notNull": false
          }
        ],
        "primaryKey": {
          "autoGenerate": true,
          "columnNames": [
            "id"
          ]
        },
        "indices": [],
        "foreignKeys": []
      },
      {
        "tableName": "qs_tiles",
        "createSql": "CREATE TABLE IF NOT EXISTS `${TABLE_NAME}` (`id` INTEGER PRIMARY KEY AUTOINCREMENT NOT NULL, `tile_id` TEXT NOT NULL, `added` INTEGER NOT NULL DEFAULT 1, `server_id` INTEGER NOT NULL DEFAULT 0, `icon_name` TEXT, `entity_id` TEXT NOT NULL, `label` TEXT NOT NULL, `subtitle` TEXT, `should_vibrate` INTEGER NOT NULL DEFAULT 0, `auth_required` INTEGER NOT NULL DEFAULT 0)",
        "fields": [
          {
            "fieldPath": "id",
            "columnName": "id",
            "affinity": "INTEGER",
            "notNull": true
          },
          {
            "fieldPath": "tileId",
            "columnName": "tile_id",
            "affinity": "TEXT",
            "notNull": true
          },
          {
            "fieldPath": "added",
            "columnName": "added",
            "affinity": "INTEGER",
            "notNull": true,
            "defaultValue": "1"
          },
          {
            "fieldPath": "serverId",
            "columnName": "server_id",
            "affinity": "INTEGER",
            "notNull": true,
            "defaultValue": "0"
          },
          {
            "fieldPath": "iconName",
            "columnName": "icon_name",
            "affinity": "TEXT",
            "notNull": false
          },
          {
            "fieldPath": "entityId",
            "columnName": "entity_id",
            "affinity": "TEXT",
            "notNull": true
          },
          {
            "fieldPath": "label",
            "columnName": "label",
            "affinity": "TEXT",
            "notNull": true
          },
          {
            "fieldPath": "subtitle",
            "columnName": "subtitle",
            "affinity": "TEXT",
            "notNull": false
          },
          {
            "fieldPath": "shouldVibrate",
            "columnName": "should_vibrate",
            "affinity": "INTEGER",
            "notNull": true,
            "defaultValue": "0"
          },
          {
            "fieldPath": "authRequired",
            "columnName": "auth_required",
            "affinity": "INTEGER",
            "notNull": true,
            "defaultValue": "0"
          }
        ],
        "primaryKey": {
          "autoGenerate": true,
          "columnNames": [
            "id"
          ]
        },
        "indices": [],
        "foreignKeys": []
      },
      {
        "tableName": "favorites",
        "createSql": "CREATE TABLE IF NOT EXISTS `${TABLE_NAME}` (`id` TEXT NOT NULL, `position` INTEGER NOT NULL, PRIMARY KEY(`id`))",
        "fields": [
          {
            "fieldPath": "id",
            "columnName": "id",
            "affinity": "TEXT",
            "notNull": true
          },
          {
            "fieldPath": "position",
            "columnName": "position",
            "affinity": "INTEGER",
            "notNull": true
          }
        ],
        "primaryKey": {
          "autoGenerate": false,
          "columnNames": [
            "id"
          ]
        },
        "indices": [],
        "foreignKeys": []
      },
      {
        "tableName": "favorite_cache",
        "createSql": "CREATE TABLE IF NOT EXISTS `${TABLE_NAME}` (`id` TEXT NOT NULL, `friendly_name` TEXT NOT NULL, `icon` TEXT, PRIMARY KEY(`id`))",
        "fields": [
          {
            "fieldPath": "id",
            "columnName": "id",
            "affinity": "TEXT",
            "notNull": true
          },
          {
            "fieldPath": "friendlyName",
            "columnName": "friendly_name",
            "affinity": "TEXT",
            "notNull": true
          },
          {
            "fieldPath": "icon",
            "columnName": "icon",
            "affinity": "TEXT",
            "notNull": false
          }
        ],
        "primaryKey": {
          "autoGenerate": false,
          "columnNames": [
            "id"
          ]
        },
        "indices": [],
        "foreignKeys": []
      },
      {
        "tableName": "camera_tiles",
        "createSql": "CREATE TABLE IF NOT EXISTS `${TABLE_NAME}` (`id` INTEGER NOT NULL, `entity_id` TEXT, `refresh_interval` INTEGER, PRIMARY KEY(`id`))",
        "fields": [
          {
            "fieldPath": "id",
            "columnName": "id",
            "affinity": "INTEGER",
            "notNull": true
          },
          {
            "fieldPath": "entityId",
            "columnName": "entity_id",
            "affinity": "TEXT",
            "notNull": false
          },
          {
            "fieldPath": "refreshInterval",
            "columnName": "refresh_interval",
            "affinity": "INTEGER",
            "notNull": false
          }
        ],
        "primaryKey": {
          "autoGenerate": false,
          "columnNames": [
            "id"
          ]
        },
        "indices": [],
        "foreignKeys": []
      },
      {
        "tableName": "entity_state_complications",
        "createSql": "CREATE TABLE IF NOT EXISTS `${TABLE_NAME}` (`id` INTEGER NOT NULL, `entity_id` TEXT NOT NULL, `show_title` INTEGER NOT NULL DEFAULT 1, `show_unit` INTEGER NOT NULL DEFAULT 0, PRIMARY KEY(`id`))",
        "fields": [
          {
            "fieldPath": "id",
            "columnName": "id",
            "affinity": "INTEGER",
            "notNull": true
          },
          {
            "fieldPath": "entityId",
            "columnName": "entity_id",
            "affinity": "TEXT",
            "notNull": true
          },
          {
            "fieldPath": "showTitle",
            "columnName": "show_title",
            "affinity": "INTEGER",
            "notNull": true,
            "defaultValue": "1"
          },
          {
            "fieldPath": "showUnit",
            "columnName": "show_unit",
            "affinity": "INTEGER",
            "notNull": true,
            "defaultValue": "0"
          }
        ],
        "primaryKey": {
          "autoGenerate": false,
          "columnNames": [
            "id"
          ]
        },
        "indices": [],
        "foreignKeys": []
      },
      {
        "tableName": "servers",
        "createSql": "CREATE TABLE IF NOT EXISTS `${TABLE_NAME}` (`id` INTEGER PRIMARY KEY AUTOINCREMENT NOT NULL, `_name` TEXT NOT NULL, `name_override` TEXT, `_version` TEXT, `device_registry_id` TEXT, `list_order` INTEGER NOT NULL, `device_name` TEXT, `external_url` TEXT NOT NULL, `internal_url` TEXT, `cloud_url` TEXT, `webhook_id` TEXT, `secret` TEXT, `cloudhook_url` TEXT, `use_cloud` INTEGER NOT NULL, `internal_ssids` TEXT NOT NULL, `prioritize_internal` INTEGER NOT NULL, `access_token` TEXT, `refresh_token` TEXT, `token_expiration` INTEGER, `token_type` TEXT, `install_id` TEXT, `user_id` TEXT, `user_name` TEXT, `user_is_owner` INTEGER, `user_is_admin` INTEGER)",
        "fields": [
          {
            "fieldPath": "id",
            "columnName": "id",
            "affinity": "INTEGER",
            "notNull": true
          },
          {
            "fieldPath": "_name",
            "columnName": "_name",
            "affinity": "TEXT",
            "notNull": true
          },
          {
            "fieldPath": "nameOverride",
            "columnName": "name_override",
            "affinity": "TEXT",
            "notNull": false
          },
          {
            "fieldPath": "_version",
            "columnName": "_version",
            "affinity": "TEXT",
            "notNull": false
          },
          {
            "fieldPath": "deviceRegistryId",
            "columnName": "device_registry_id",
            "affinity": "TEXT",
            "notNull": false
          },
          {
            "fieldPath": "listOrder",
            "columnName": "list_order",
            "affinity": "INTEGER",
            "notNull": true
          },
          {
            "fieldPath": "deviceName",
            "columnName": "device_name",
            "affinity": "TEXT",
            "notNull": false
          },
          {
            "fieldPath": "connection.externalUrl",
            "columnName": "external_url",
            "affinity": "TEXT",
            "notNull": true
          },
          {
            "fieldPath": "connection.internalUrl",
            "columnName": "internal_url",
            "affinity": "TEXT",
            "notNull": false
          },
          {
            "fieldPath": "connection.cloudUrl",
            "columnName": "cloud_url",
            "affinity": "TEXT",
            "notNull": false
          },
          {
            "fieldPath": "connection.webhookId",
            "columnName": "webhook_id",
            "affinity": "TEXT",
            "notNull": false
          },
          {
            "fieldPath": "connection.secret",
            "columnName": "secret",
            "affinity": "TEXT",
            "notNull": false
          },
          {
            "fieldPath": "connection.cloudhookUrl",
            "columnName": "cloudhook_url",
            "affinity": "TEXT",
            "notNull": false
          },
          {
            "fieldPath": "connection.useCloud",
            "columnName": "use_cloud",
            "affinity": "INTEGER",
            "notNull": true
          },
          {
            "fieldPath": "connection.internalSsids",
            "columnName": "internal_ssids",
            "affinity": "TEXT",
            "notNull": true
          },
          {
            "fieldPath": "connection.prioritizeInternal",
            "columnName": "prioritize_internal",
            "affinity": "INTEGER",
            "notNull": true
          },
          {
            "fieldPath": "session.accessToken",
            "columnName": "access_token",
            "affinity": "TEXT",
            "notNull": false
          },
          {
            "fieldPath": "session.refreshToken",
            "columnName": "refresh_token",
            "affinity": "TEXT",
            "notNull": false
          },
          {
            "fieldPath": "session.tokenExpiration",
            "columnName": "token_expiration",
            "affinity": "INTEGER",
            "notNull": false
          },
          {
            "fieldPath": "session.tokenType",
            "columnName": "token_type",
            "affinity": "TEXT",
            "notNull": false
          },
          {
            "fieldPath": "session.installId",
            "columnName": "install_id",
            "affinity": "TEXT",
            "notNull": false
          },
          {
            "fieldPath": "user.id",
            "columnName": "user_id",
            "affinity": "TEXT",
            "notNull": false
          },
          {
            "fieldPath": "user.name",
            "columnName": "user_name",
            "affinity": "TEXT",
            "notNull": false
          },
          {
            "fieldPath": "user.isOwner",
            "columnName": "user_is_owner",
            "affinity": "INTEGER",
            "notNull": false
          },
          {
            "fieldPath": "user.isAdmin",
            "columnName": "user_is_admin",
            "affinity": "INTEGER",
            "notNull": false
          }
        ],
        "primaryKey": {
          "autoGenerate": true,
          "columnNames": [
            "id"
          ]
        },
        "indices": [],
        "foreignKeys": []
      },
      {
        "tableName": "settings",
        "createSql": "CREATE TABLE IF NOT EXISTS `${TABLE_NAME}` (`id` INTEGER NOT NULL, `websocket_setting` TEXT NOT NULL, `sensor_update_frequency` TEXT NOT NULL, PRIMARY KEY(`id`))",
        "fields": [
          {
            "fieldPath": "id",
            "columnName": "id",
            "affinity": "INTEGER",
            "notNull": true
          },
          {
            "fieldPath": "websocketSetting",
            "columnName": "websocket_setting",
            "affinity": "TEXT",
            "notNull": true
          },
          {
            "fieldPath": "sensorUpdateFrequency",
            "columnName": "sensor_update_frequency",
            "affinity": "TEXT",
            "notNull": true
          }
        ],
        "primaryKey": {
          "autoGenerate": false,
          "columnNames": [
            "id"
          ]
        },
        "indices": [],
        "foreignKeys": []
      }
    ],
    "views": [],
    "setupQueries": [
      "CREATE TABLE IF NOT EXISTS room_master_table (id INTEGER PRIMARY KEY,identity_hash TEXT)",
      "INSERT OR REPLACE INTO room_master_table (id,identity_hash) VALUES(42, '0f958ba55579b89c341335658fd01d2a')"
    ]
  }
}